gcn_kafka/__init__.py
gcn_kafka/_version.py
gcn_kafka/core.py
gcn_kafka/env.py
gcn_kafka/py.typed
gcn_kafka-0.3.4.dist-info/licenses/LICENSE.txt
gcn_kafka-0.3.4.dist-info/METADATA
gcn_kafka-0.3.4.dist-info/WHEEL
gcn_kafka-0.3.4.dist-info/top_level.txt
gcn_kafka-0.3.4.dist-info/RECORD
