Metadata-Version: 2.4
Name: gcn-kafka
Version: 0.3.4
Summary: Kafka client for NASA's General Coordinates Network (GCN)
Author-email: Leo Singer <leo.p.singer@nasa.gov>, Tom Barclay <tb@umbc.edu>, Eric Burns <ericburns@lsu.edu>
License-Expression: CC0-1.0
Project-URL: source, https://github.com/nasa-gcn/gcn-kafka-python
Classifier: Intended Audience :: Education
Classifier: Intended Audience :: Science/Research
Classifier: Topic :: Scientific/Engineering :: Astronomy
Classifier: Topic :: Scientific/Engineering :: Physics
Classifier: Topic :: System :: Networking
Classifier: Typing :: Typed
Requires-Python: >=3.9
License-File: LICENSE.txt
Requires-Dist: certifi
Requires-Dist: confluent-kafka>=2.11.0
Provides-Extra: test
Requires-Dist: pytest; extra == "test"
Dynamic: license-file
